rowSumExplorer/__init__.py
rowSumExplorer/rowSumExplorer.py
rowSumExplorer-1.5.dist-info/LICENSE
rowSumExplorer-1.5.dist-info/METADATA
rowSumExplorer-1.5.dist-info/WHEEL
rowSumExplorer-1.5.dist-info/top_level.txt
rowSumExplorer-1.5.dist-info/RECORD
