Metadata-Version: 2.1
Name: rowSumExplorer
Version: 1.5
Summary: Making dataframes from an excel tabled based on target sum column
Home-page: https://github.com/oLiontas/RowSumExplorer
Author: Leonidas Dosas
Author-email: oLiontas <liontas76@gmail.com>
License: MIT
Project-URL: Homepage, https://github.com/oLiontas/RowSumExplorer
Project-URL: Bug Tracker, https://github.com/oLiontas/RowSumExplorer/issues
Classifier: Programming Language :: Python :: 3
Classifier: License :: OSI Approved :: MIT License
Classifier: Operating System :: OS Independent
Requires-Python: >=3.0
License-File: LICENSE
Requires-Dist: pandas
Requires-Dist: openpyxl
